pg_explain_locks.py
pg_explain_locks-0.0.3.dist-info/LICENSE
pg_explain_locks-0.0.3.dist-info/METADATA
pg_explain_locks-0.0.3.dist-info/WHEEL
pg_explain_locks-0.0.3.dist-info/entry_points.txt
pg_explain_locks-0.0.3.dist-info/top_level.txt
pg_explain_locks-0.0.3.dist-info/RECORD
