Metadata-Version: 2.1
Name: pg-explain-locks
Version: 0.0.3
Summary: Postgres utility to show what locks will be acquired by a given query.
Home-page: https://github.com/AdmTal/PostgreSQL-Query-Lock-Explainer
Author: Adam Tal
Author-email: admtal@gmail.com
License: UNKNOWN
Platform: UNKNOWN
Classifier: Programming Language :: Python :: 3
Classifier: License :: OSI Approved :: MIT License
Classifier: Operating System :: OS Independent
Requires-Python: >=3.6
Requires-Dist: prettytable
Requires-Dist: psycopg2
